{
  "payments": [
    {
      "month": "Junho",
      "year": 2021,
      "description": "Salário",
      "value": 1500,
      "id": 1
    },
    {
      "month": "Junho",
      "year": 2021,
      "description": "Freelance",
      "value": 500,
      "id": 2
    },
    {
      "month": "Abril",
      "year": 1900,
      "description": "Teste",
      "value": 1,
      "id": 3
    }
  ],
  "purchases": [
    {
      "id": 1,
      "name": "Aluguel de Bike",
      "value": 20,
      "category": "Lazer"
    }
  ]
}